pyind/__init__.py
pyind/crossover.py
pyind/defaults.py
pyind/mutation.py
pyind/pyind.py
pyind/selection.py
pyind/trush.py
pyind/util.py
pyind-1.2.dist-info/METADATA
pyind-1.2.dist-info/WHEEL
pyind-1.2.dist-info/top_level.txt
pyind-1.2.dist-info/RECORD
