Metadata-Version: 2.1
Name: pyind
Version: 1.2
Summary: A genetic algorithm library in Python3
Home-page: https://github.com/chankane/pyind
Author: chankane
Author-email: brawnychocolate@gmail.com
License: UNKNOWN
Keywords: pyind genetic ga GA
Platform: UNKNOWN
Classifier: Programming Language :: Python :: 3.7
Classifier: License :: OSI Approved :: MIT License
Classifier: Operating System :: OS Independent
Requires-Dist: numpy
